{"title":"Labyrinth.Of.The.Senses.DVDRip.XxX.avi","uid":8764394,"size":741513216,"categoryP":"porn","categoryS":"movies","magnet":"?xt=urn:btih:0dc05e5df98439097403f7e9fe32077aac7e2dbb&amp;dn=Labyrinth.Of.The.Senses.DVDRip.XxX.avi&amp;tr=udp%3A%2F%2Ftracker.openbittorrent.com%3A80&amp;tr=udp%3A%2F%2Fopen.demonii.com%3A1337&amp;tr=udp%3A%2F%2Ftracker.coppersurfer.tk%3A6969&amp;tr=udp%3A%2F%2Fexodus.desync.com%3A6969","seeders":1,"leechers":0,"uploader":"handsome_hulk1253","files":1,"time":1375300607,"description":"Screenshots\n\n &lt;a href=&quot;\nhttp://adultxpictures.com/xxx/2p1&quot; rel=&quot;nofollow&quot; target=&quot;_NEW&quot;&gt;\nhttp://adultxpictures.com/xxx/2p1&lt;/a&gt; &lt;a href=&quot;\nhttp://adultxpictures.com/xxx/2p8&quot; rel=&quot;nofollow&quot; target=&quot;_NEW&quot;&gt;\nhttp://adultxpictures.com/xxx/2p8&lt;/a&gt;","torrent":{"xt":"urn:btih:0dc05e5df98439097403f7e9fe32077aac7e2dbb","amp;dn":"Labyrinth.Of.The.Senses.DVDRip.XxX.avi","amp;tr":["udp%3A%2F%2Ftracker.openbittorrent.com%3A80","udp%3A%2F%2Fopen.demonii.com%3A1337","udp%3A%2F%2Ftracker.coppersurfer.tk%3A6969","udp%3A%2F%2Fexodus.desync.com%3A6969"],"infoHash":"0dc05e5df98439097403f7e9fe32077aac7e2dbb","infoHashBuffer":{"type":"Buffer","data":[13,192,94,93,249,132,57,9,116,3,247,233,254,50,7,122,172,126,45,187]},"announce":[],"urlList":[]}}