{"title":"Tanya Tate - Role Playing HD 1080p","uid":11859689,"size":1554826304,"categoryP":"porn","categoryS":"hd___movies","magnet":"?xt=urn:btih:1bfaf154e1e6b4c313479e6e6013e4ad77a15c0f&amp;dn=Tanya+Tate+-+Role+Playing+HD+1080p&amp;tr=udp%3A%2F%2Ftracker.openbittorrent.com%3A80&amp;tr=udp%3A%2F%2Fopen.demonii.com%3A1337&amp;tr=udp%3A%2F%2Ftracker.coppersurfer.tk%3A6969&amp;tr=udp%3A%2F%2Fexodus.desync.com%3A6969","seeders":1,"leechers":2,"uploader":"ElitePorn","files":1,"time":1430233986,"description":"Tanya Tate - Role Playing HD 1080p\n----------------------------------\n\nScreenshots:\n------------\n &lt;a href=&quot;\nhttp://picturescream.asia/soft/bbX&quot; rel=&quot;nofollow&quot; target=&quot;_NEW&quot;&gt;\nhttp://picturescream.asia/soft/bbX&lt;/a&gt;\n &lt;a href=&quot;\nhttp://picturescream.asia/soft/bby&quot; rel=&quot;nofollow&quot; target=&quot;_NEW&quot;&gt;\nhttp://picturescream.asia/soft/bby&lt;/a&gt;\n &lt;a href=&quot;\nhttp://picturescream.asia/soft/bkI&quot; rel=&quot;nofollow&quot; target=&quot;_NEW&quot;&gt;\nhttp://picturescream.asia/soft/bkI&lt;/a&gt;\n &lt;a href=&quot;\nhttp://picturescream.asia/soft/bkt&quot; rel=&quot;nofollow&quot; target=&quot;_NEW&quot;&gt;\nhttp://picturescream.asia/soft/bkt&lt;/a&gt;\n &lt;a href=&quot;\nhttp://picturescream.asia/soft/bk2&quot; rel=&quot;nofollow&quot; target=&quot;_NEW&quot;&gt;\nhttp://picturescream.asia/soft/bk2&lt;/a&gt;\n &lt;a href=&quot;\nhttp://picturescream.asia/soft/bkJ&quot; rel=&quot;nofollow&quot; target=&quot;_NEW&quot;&gt;\nhttp://picturescream.asia/soft/bkJ&lt;/a&gt;\n\n\nDuration: 55:13, Format: mp4, Resolution: 1920x1080, Size: 1.448 GB\n\n...~~~:::For More Porn Torrents:::~~~... &lt;a href=&quot;\nhttps://thepiratebay.se/user/ElitePorn/&quot; rel=&quot;nofollow&quot; target=&quot;_NEW&quot;&gt;\nhttps://thepiratebay.se/user/ElitePorn/&lt;/a&gt;","torrent":{"xt":"urn:btih:1bfaf154e1e6b4c313479e6e6013e4ad77a15c0f","amp;dn":"Tanya+Tate+-+Role+Playing+HD+1080p","amp;tr":["udp%3A%2F%2Ftracker.openbittorrent.com%3A80","udp%3A%2F%2Fopen.demonii.com%3A1337","udp%3A%2F%2Ftracker.coppersurfer.tk%3A6969","udp%3A%2F%2Fexodus.desync.com%3A6969"],"infoHash":"1bfaf154e1e6b4c313479e6e6013e4ad77a15c0f","infoHashBuffer":{"type":"Buffer","data":[27,250,241,84,225,230,180,195,19,71,158,110,96,19,228,173,119,161,92,15]},"announce":[],"urlList":[]}}