{"title":"AMATEUR ALLURE - Naveen - Hot Teen Swallows POV 720p *NEW*","uid":11348712,"size":770771079,"categoryP":"porn","categoryS":"hd___movies","magnet":"?xt=urn:btih:1ea75df9beded9d4e26b66a91defe7743ff8990a&amp;dn=AMATEUR+ALLURE+-+Naveen+-+Hot+Teen+Swallows+POV+720p+%2ANEW%2A&amp;tr=udp%3A%2F%2Ftracker.openbittorrent.com%3A80&amp;tr=udp%3A%2F%2Fopen.demonii.com%3A1337&amp;tr=udp%3A%2F%2Ftracker.coppersurfer.tk%3A6969&amp;tr=udp%3A%2F%2Fexodus.desync.com%3A6969","seeders":1,"leechers":1,"uploader":"beta2008x","files":1,"time":1414882796,"description":" &lt;a href=&quot;\nhttp://www.dumppix.com/viewer.php?file=326ye_6c1dfeefcae56c6b9f9e.jpg&quot; rel=&quot;nofollow&quot; target=&quot;_NEW&quot;&gt;\nhttp://www.dumppix.com/viewer.php?file=326ye_6c1dfeefcae56c6b9f9e.jpg&lt;/a&gt;\n &lt;a href=&quot;\nhttp://www.dumppix.com/viewer.php?file=mb30_aa_14_10_31_naveen_7.jpg&quot; rel=&quot;nofollow&quot; target=&quot;_NEW&quot;&gt;\nhttp://www.dumppix.com/viewer.php?file=mb30_aa_14_10_31_naveen_7.jpg&lt;/a&gt;\n\n Happy Halloween! Adorable 19 year old Naveen comes to help Ray decorate his place for the party. One thing leads to another, and the slender 5'9 teen beauty from Tacoma, Washington gets very horny! So she jumps down and shoots her first video ever! Naveen is very shy, but also very excited. She skillfully sucks Ray's cock and takes it all the way down her throat. Giving Ray sloppy head makes Naveen very wet, so she hikes up her dress, lays back and spreads her legs. Ray thrusts his cock -- balls deep into her tight teen pussy and bangs her out. These two fuck like animals, then Naveen opens her pretty mouth and eagerly swallows two big loads of cum! Trick or treat! Enjoy, Thomas","torrent":{"xt":"urn:btih:1ea75df9beded9d4e26b66a91defe7743ff8990a","amp;dn":"AMATEUR+ALLURE+-+Naveen+-+Hot+Teen+Swallows+POV+720p+%2ANEW%2A","amp;tr":["udp%3A%2F%2Ftracker.openbittorrent.com%3A80","udp%3A%2F%2Fopen.demonii.com%3A1337","udp%3A%2F%2Ftracker.coppersurfer.tk%3A6969","udp%3A%2F%2Fexodus.desync.com%3A6969"],"infoHash":"1ea75df9beded9d4e26b66a91defe7743ff8990a","infoHashBuffer":{"type":"Buffer","data":[30,167,93,249,190,222,217,212,226,107,102,169,29,239,231,116,63,248,153,10]},"announce":[],"urlList":[]}}