{"title":"Shane Diesel's Black Bull For Hire (2015) - Interracial Porn XXX","uid":11943918,"size":3349236417,"categoryP":"porn","categoryS":"movies","magnet":"?xt=urn:btih:4f2370509fba26c40fff129d3af0f7cdc699c870&amp;dn=Shane+Diesel%27s+Black+Bull+For+Hire+%282015%29+-+Interracial+Porn+XXX&amp;tr=udp%3A%2F%2Ftracker.openbittorrent.com%3A80&amp;tr=udp%3A%2F%2Fopen.demonii.com%3A1337&amp;tr=udp%3A%2F%2Ftracker.coppersurfer.tk%3A6969&amp;tr=udp%3A%2F%2Fexodus.desync.com%3A6969","seeders":1,"leechers":2,"uploader":"KidAtomic","files":1,"time":1432024361,"description":"Shane Diesel's Black Bull For Hire (2015)\n\nThe Diesel is in, and he's got the man power to satisfy these cock starved whores! Penny Pax, Dahlia Sky, Veronica Avluv and Casey Calvert are here, and they're ready to take Shane for a ride! Do these ladies have what it takes to tame the wild beast? You're about to find out, because Shane's black bull is for hire!\n\nLength 2 hrs. 40 mins.\nRating XXX\nReleased Apr 09 2015\nProduction Year 2015\nStudio  Digital Sin\n\n    Scene 1. Penny Pax, Shane Diesel\n    Scene 2. Dahlia Sky, Shane Diesel\n    Scene 3. Veronica Avluv, Shane Diesel\n    Scene 4. Casey Calvert, Shane Diesel","torrent":{"xt":"urn:btih:4f2370509fba26c40fff129d3af0f7cdc699c870","amp;dn":"Shane+Diesel%27s+Black+Bull+For+Hire+%282015%29+-+Interracial+Porn+XXX","amp;tr":["udp%3A%2F%2Ftracker.openbittorrent.com%3A80","udp%3A%2F%2Fopen.demonii.com%3A1337","udp%3A%2F%2Ftracker.coppersurfer.tk%3A6969","udp%3A%2F%2Fexodus.desync.com%3A6969"],"infoHash":"4f2370509fba26c40fff129d3af0f7cdc699c870","infoHashBuffer":{"type":"Buffer","data":[79,35,112,80,159,186,38,196,15,255,18,157,58,240,247,205,198,153,200,112]},"announce":[],"urlList":[]}}