{"title":"Eminem Freestyle RARE mp3","uid":6846448,"size":1426360,"categoryP":"audio","categoryS":"music","magnet":"?xt=urn:btih:52225a10753ea4b331a83629c38e20e9dbe734ca&amp;dn=Eminem+Freestyle+RARE+mp3&amp;tr=udp%3A%2F%2Ftracker.openbittorrent.com%3A80&amp;tr=udp%3A%2F%2Fopen.demonii.com%3A1337&amp;tr=udp%3A%2F%2Ftracker.coppersurfer.tk%3A6969&amp;tr=udp%3A%2F%2Fexodus.desync.com%3A6969","seeders":1,"leechers":0,"uploader":"TUXtorrent","files":1,"time":1322363166,"description":"Eminem Freestyle RARE mp3","torrent":{"xt":"urn:btih:52225a10753ea4b331a83629c38e20e9dbe734ca","amp;dn":"Eminem+Freestyle+RARE+mp3","amp;tr":["udp%3A%2F%2Ftracker.openbittorrent.com%3A80","udp%3A%2F%2Fopen.demonii.com%3A1337","udp%3A%2F%2Ftracker.coppersurfer.tk%3A6969","udp%3A%2F%2Fexodus.desync.com%3A6969"],"infoHash":"52225a10753ea4b331a83629c38e20e9dbe734ca","infoHashBuffer":{"type":"Buffer","data":[82,34,90,16,117,62,164,179,49,168,54,41,195,142,32,233,219,231,52,202]},"announce":[],"urlList":[]}}