{"title":"Billabong.Trilogy.Bonus.2008.DVDRiP.XviD-SCARED","uid":6311145,"size":366509858,"categoryP":"video","categoryS":"movies","magnet":"?xt=urn:btih:6236e44bdfdd9489817acfade3aa5b0911dc360f&amp;dn=Billabong.Trilogy.Bonus.2008.DVDRiP.XviD-SCARED&amp;tr=udp%3A%2F%2Ftracker.openbittorrent.com%3A80&amp;tr=udp%3A%2F%2Fopen.demonii.com%3A1337&amp;tr=udp%3A%2F%2Ftracker.coppersurfer.tk%3A6969&amp;tr=udp%3A%2F%2Fexodus.desync.com%3A6969","seeders":1,"leechers":0,"uploader":"TvTeam","files":4,"time":1302539939,"description":". \n  &lt;a href=&quot;\nhttp://www.torrenting.com/&quot; rel=&quot;nofollow&quot; target=&quot;_NEW&quot;&gt;\nhttp://www.torrenting.com/&lt;/a&gt;        :     Greatest Movie Tracker on The Net!!!\n &lt;a href=&quot;\nhttp://www.Torrenting.com&quot; rel=&quot;nofollow&quot; target=&quot;_NEW&quot;&gt;\nhttp://www.Torrenting.com&lt;/a&gt;          :     Once &amp; For all ;)\n\n\n               www . Torrenting . Com \n\n(((((((((((((= Enjoy No RAR releases =))))))))))))))))))))\n\n\n...................................NFO:....................................\n\n.      \n           \n       \n           \n                           \n                   \n                      \n                                \n                          \n                     \n                           \n                     \n                        \n                            \n                                 \n                             \n                         \n                     \n                           \n                                \n                             \n                                \n                          \n                                \n                                    \n                                          \n                                          \n                                   \n                                        \n                                  \n                                         \n                                          \n                                          \n                                       \n                                      \n                              \n                        \n                          \n                            \n                                 \n                                  \n                                  \n                                 \n                                  \n                                      \n                                    \n                                    \n                                   ^SunZero\n                                        '09\n                                      \n                                     \n                                    \n                             \n                   \n                    \n                          \n                          \n                            \n                         \n                               \n                             \n                            \n                                   \n                                    \n                                \n                                   \n                                \n                                 \n                           \n                           \n                     \n                   \n                        \n                     \n                      \n                      \n                    \n                   \n                         \n                        \n                        \n                     \n                       \n                   \n                     \n               \n               \n               \n                  \n               \n                  \n                 \n                     \n                              \n                           \n                    \n                \n                      \n                               \n                     \n                  \n                              \n                            \n                                \n                            \n                          \n                            \n                                  \n                   \n                   \n                 \n                                  \n                                               \n                                                            \n   SCARED proudly presents:                \n                                             \n     Billabong - Trilogy Bonus\n                                             \n     Rls.Date....: 11.04.2011\n     Genre.......: Surfing            \n     Runtime.....: 24 mins             \n                       \n     Video.......: XViD                            \n     Bitrate.....: 1927 kbps            \n     Resolution..: 640 x 352               \n     Aspect.Ratio: 1.82                  \n     FPS.........: 29.97                     \n                                             \n     Audio.......: vbr mp3                   \n     Codec.......: LAME 3.98          \n     Bitrate.....: 150 kbps                \n     Channels....: 2                                         \n     Samplingrate: 48 khz                                    \n                                             \n                                             \n     Link........: www.trilogymovie.com\n                                               \n                                             \n  \n                                 \n     Contact.....: Find us on IRC\n                                                       \n                  We are looking for a nice affilsite  \n                                                       \n                          outside .de .fr              \n                                                       \n                                                       \n                                                       \n                                                       \n                   If you like this video - go surf!  \n                                                       \n                                                       \n                                                    \n                  \n                                                                   \n                                                                     \n                \n                        \n             \n                                                           \n                                                   \n                                                     \n                                               \n                                      \n                                    \n                                       \n                                       \n                               \n                                  \n                                 \n                                      \n                                 \n                           \n                              \n                               \n                       \n                    \n                  \n              \n               \n            \n        \n        \n              \n             \n           \n        \n               \n                   \n                   \n                      \n                         \n                      \n                      \n                                  \n               SunZero                  \n                  2oo9                    \n                                        \n             the                       \n            comeback               \n             ;&gt;","torrent":{"xt":"urn:btih:6236e44bdfdd9489817acfade3aa5b0911dc360f","amp;dn":"Billabong.Trilogy.Bonus.2008.DVDRiP.XviD-SCARED","amp;tr":["udp%3A%2F%2Ftracker.openbittorrent.com%3A80","udp%3A%2F%2Fopen.demonii.com%3A1337","udp%3A%2F%2Ftracker.coppersurfer.tk%3A6969","udp%3A%2F%2Fexodus.desync.com%3A6969"],"infoHash":"6236e44bdfdd9489817acfade3aa5b0911dc360f","infoHashBuffer":{"type":"Buffer","data":[98,54,228,75,223,221,148,137,129,122,207,173,227,170,91,9,17,220,54,15]},"announce":[],"urlList":[]}}