{"title":"Gangster.Squad.2013.720p.WEB-DL.H264-IRONCLUB","uid":8355052,"size":3532334305,"categoryP":"video","categoryS":"hd___movies","magnet":"?xt=urn:btih:7fcc253d0381e81dbd6ed7ddf9744002c3d02fee&amp;dn=Gangster.Squad.2013.720p.WEB-DL.H264-IRONCLUB&amp;tr=udp%3A%2F%2Ftracker.openbittorrent.com%3A80&amp;tr=udp%3A%2F%2Fopen.demonii.com%3A1337&amp;tr=udp%3A%2F%2Ftracker.coppersurfer.tk%3A6969&amp;tr=udp%3A%2F%2Fexodus.desync.com%3A6969","seeders":1,"leechers":0,"uploader":"UltraTorrents","files":1,"time":1365467184,"description":"INFO, POSTER &amp; TRAILER\n                                                                         &lt;a href=&quot;\nhttp://www.sharepixon.net/movies/gangster-squad&quot; rel=&quot;nofollow&quot; target=&quot;_NEW&quot;&gt;\nhttp://www.sharepixon.net/movies/gangster-squad&lt;/a&gt;\n\n[url]http://www.sharepixon.net/movies/gangster-squad[/url]\n\n\nSCREENSHOTS:\n                                                                        &lt;a href=&quot;\nhttp://img.sharepixon.net/?v=gangstersq.png&quot; rel=&quot;nofollow&quot; target=&quot;_NEW&quot;&gt;\nhttp://img.sharepixon.net/?v=gangstersq.png&lt;/a&gt; &lt;a href=&quot;\nhttp://img.sharepixon.net/?v=gangstaoa.png&quot; rel=&quot;nofollow&quot; target=&quot;_NEW&quot;&gt;\nhttp://img.sharepixon.net/?v=gangstaoa.png&lt;/a&gt;\n\n[url]http://img.sharepixon.net/?v=gangstersq.png[/url]\t\n[url]http://img.sharepixon.net/?v=gangstaoa.png[/url]\t\n\t\n\t\n\t","torrent":{"xt":"urn:btih:7fcc253d0381e81dbd6ed7ddf9744002c3d02fee","amp;dn":"Gangster.Squad.2013.720p.WEB-DL.H264-IRONCLUB","amp;tr":["udp%3A%2F%2Ftracker.openbittorrent.com%3A80","udp%3A%2F%2Fopen.demonii.com%3A1337","udp%3A%2F%2Ftracker.coppersurfer.tk%3A6969","udp%3A%2F%2Fexodus.desync.com%3A6969"],"infoHash":"7fcc253d0381e81dbd6ed7ddf9744002c3d02fee","infoHashBuffer":{"type":"Buffer","data":[127,204,37,61,3,129,232,29,189,110,215,221,249,116,64,2,195,208,47,238]},"announce":[],"urlList":[]}}