{"title":"Between The Headlines - A Lesbian Porn Parody DVDRip.mp4","uid":11200238,"size":1741684860,"categoryP":"porn","categoryS":"movies","magnet":"?xt=urn:btih:bb6caf8c3872a87758ee5d2b2ae60ecff50b9746&amp;dn=Between+The+Headlines+-+A+Lesbian+Porn+Parody+DVDRip.mp4&amp;tr=udp%3A%2F%2Ftracker.openbittorrent.com%3A80&amp;tr=udp%3A%2F%2Fopen.demonii.com%3A1337&amp;tr=udp%3A%2F%2Ftracker.coppersurfer.tk%3A6969&amp;tr=udp%3A%2F%2Fexodus.desync.com%3A6969","seeders":1,"leechers":6,"uploader":"PornKing","files":-1,"time":1413162131,"description":"Between The Headlines - A Lesbian Porn Parody DVDRip.mp4\n\nNina Hartley, Lotus Lain, Lily Cade, Aaliyah Love, Vanessa Veracruz, Aiden Starr, Ela Darling, Zoey Monroe.\n\n2014, All Girl, Girl-Girl, Feature, Plot Based, Lesbian, Parody, Spoof, DVDRip, XXX, Adult\n\n720 x 404\n\n02:13:54\n\n1.62 GB\n\nScreens\n &lt;a href=&quot;\nhttp://imgcentral.com/viewer.php?file=70835599542364090632.jpg&quot; rel=&quot;nofollow&quot; target=&quot;_NEW&quot;&gt;\nhttp://imgcentral.com/viewer.php?file=70835599542364090632.jpg&lt;/a&gt;\n &lt;a href=&quot;\nhttp://imgcentral.com/viewer.php?file=53583097738670442916.jpg&quot; rel=&quot;nofollow&quot; target=&quot;_NEW&quot;&gt;\nhttp://imgcentral.com/viewer.php?file=53583097738670442916.jpg&lt;/a&gt;\n &lt;a href=&quot;\nhttp://imgcentral.com/viewer.php?file=15609114709039391883.jpg&quot; rel=&quot;nofollow&quot; target=&quot;_NEW&quot;&gt;\nhttp://imgcentral.com/viewer.php?file=15609114709039391883.jpg&lt;/a&gt;","torrent":{"xt":"urn:btih:bb6caf8c3872a87758ee5d2b2ae60ecff50b9746","amp;dn":"Between+The+Headlines+-+A+Lesbian+Porn+Parody+DVDRip.mp4","amp;tr":["udp%3A%2F%2Ftracker.openbittorrent.com%3A80","udp%3A%2F%2Fopen.demonii.com%3A1337","udp%3A%2F%2Ftracker.coppersurfer.tk%3A6969","udp%3A%2F%2Fexodus.desync.com%3A6969"],"infoHash":"bb6caf8c3872a87758ee5d2b2ae60ecff50b9746","infoHashBuffer":{"type":"Buffer","data":[187,108,175,140,56,114,168,119,88,238,93,43,42,230,14,207,245,11,151,70]},"announce":[],"urlList":[]}}