{"title":"[MarcDorcel] Ca Baise Au Bureau [2010] (Split Scenes)","uid":15008235,"size":2071973307,"categoryP":"porn","categoryS":"movies","magnet":"?xt=urn:btih:c231a85c5b4f036fa79ba1653f594b3ab1f350d7&amp;dn=%5BMarcDorcel%5D+Ca+Baise+Au+Bureau+%5B2010%5D+%28Split+Scenes%29&amp;tr=udp%3A%2F%2Ftracker.leechers-paradise.org%3A6969&amp;tr=udp%3A%2F%2Fzer0day.ch%3A1337&amp;tr=udp%3A%2F%2Fopen.demonii.com%3A1337&amp;tr=udp%3A%2F%2Ftracker.coppersurfer.tk%3A6969&amp;tr=udp%3A%2F%2Fexodus.desync.com%3A6969","seeders":1,"leechers":1,"uploader":"SudoSu","files":1,"time":1466409392,"description":"http://youpornbook.com\r\n\r\n-------------------------\r\n ... : Screenshots : ... \r\n-------------------------\r\n\r\n \nhttp://imgscorpion.com/?v=782491\r\n \nhttp://imgscorpion.com/?v=118392\r\n \nhttp://imgscorpion.com/?v=588042\r\n\r\n\r\n-------------------------\r\n ... : Starring : ... \r\n-------------------------\r\n\r\nAnna Polina, Aline Delacour, Lea Fast, Penelope Tiger, Aurora Viper, Pamela, Maeva, Mike Angelo\r\n\r\n\r\n-------------------------\r\n ... : Description : ... \r\n-------------------------\r\n\r\nApparently, this is a normal day at the Dorcel production offices.\r\nScene 1: Blonde nailed on office desk\r\nScene 2: Anna Polina gives a blowjow in casting\r\nScene 3: Shooting a scene with Lea Fast\r\nScene 4: &quot;Meeting&quot; the receptionist with Aline Delacour - great scene\r\nScene 5: Aurora Viper on the desk on the cutting room....\r\nScene 6: Anna Polina looking gorgeous having sex over the desk\r\n\r\n\r\nMore exclusive porn at:  https://thepiratebay.se/user/SudoSu/","torrent":{"xt":"urn:btih:c231a85c5b4f036fa79ba1653f594b3ab1f350d7","amp;dn":"%5BMarcDorcel%5D+Ca+Baise+Au+Bureau+%5B2010%5D+%28Split+Scenes%29","amp;tr":["udp%3A%2F%2Ftracker.leechers-paradise.org%3A6969","udp%3A%2F%2Fzer0day.ch%3A1337","udp%3A%2F%2Fopen.demonii.com%3A1337","udp%3A%2F%2Ftracker.coppersurfer.tk%3A6969","udp%3A%2F%2Fexodus.desync.com%3A6969"],"infoHash":"c231a85c5b4f036fa79ba1653f594b3ab1f350d7","infoHashBuffer":{"type":"Buffer","data":[194,49,168,92,91,79,3,111,167,155,161,101,63,89,75,58,177,243,80,215]},"announce":[],"urlList":[]}}