{"title":"Kagney Linn Karter - Kagney Linn Massively Dicked Down HD 720p","uid":9561578,"size":1111683310,"categoryP":"porn","categoryS":"hd___movies","magnet":"?xt=urn:btih:d0d1f37890afaf27100e808f5f7e970b05762fc4&amp;dn=Kagney+Linn+Karter+-+Kagney+Linn+Massively+Dicked+Down+HD+720p&amp;tr=udp%3A%2F%2Ftracker.openbittorrent.com%3A80&amp;tr=udp%3A%2F%2Fopen.demonii.com%3A1337&amp;tr=udp%3A%2F%2Ftracker.coppersurfer.tk%3A6969&amp;tr=udp%3A%2F%2Fexodus.desync.com%3A6969","seeders":1,"leechers":0,"uploader":"ElitePorn","files":-1,"time":1391439725,"description":"Kagney Linn Karter - Kagney Linn Massively Dicked Down HD 720p\n--------------------------------------------------------------\n\nScreenshots:\n------------\n\n &lt;a href=&quot;\nhttp://picturescream.asia/soft/RkV&quot; rel=&quot;nofollow&quot; target=&quot;_NEW&quot;&gt;\nhttp://picturescream.asia/soft/RkV&lt;/a&gt;\n &lt;a href=&quot;\nhttp://picturescream.asia/soft/Rk0&quot; rel=&quot;nofollow&quot; target=&quot;_NEW&quot;&gt;\nhttp://picturescream.asia/soft/Rk0&lt;/a&gt;\n &lt;a href=&quot;\nhttp://picturescream.asia/soft/RkZ&quot; rel=&quot;nofollow&quot; target=&quot;_NEW&quot;&gt;\nhttp://picturescream.asia/soft/RkZ&lt;/a&gt;\n &lt;a href=&quot;\nhttp://picturescream.asia/soft/Rkg&quot; rel=&quot;nofollow&quot; target=&quot;_NEW&quot;&gt;\nhttp://picturescream.asia/soft/Rkg&lt;/a&gt;\n &lt;a href=&quot;\nhttp://picturescream.asia/soft/RkO&quot; rel=&quot;nofollow&quot; target=&quot;_NEW&quot;&gt;\nhttp://picturescream.asia/soft/RkO&lt;/a&gt;\n &lt;a href=&quot;\nhttp://picturescream.asia/soft/Rkq&quot; rel=&quot;nofollow&quot; target=&quot;_NEW&quot;&gt;\nhttp://picturescream.asia/soft/Rkq&lt;/a&gt;\n &lt;a href=&quot;\nhttp://picturescream.asia/soft/Rk9&quot; rel=&quot;nofollow&quot; target=&quot;_NEW&quot;&gt;\nhttp://picturescream.asia/soft/Rk9&lt;/a&gt;\n &lt;a href=&quot;\nhttp://picturescream.asia/soft/RkN&quot; rel=&quot;nofollow&quot; target=&quot;_NEW&quot;&gt;\nhttp://picturescream.asia/soft/RkN&lt;/a&gt;\n &lt;a href=&quot;\nhttp://picturescream.asia/soft/Rkn&quot; rel=&quot;nofollow&quot; target=&quot;_NEW&quot;&gt;\nhttp://picturescream.asia/soft/Rkn&lt;/a&gt;\n &lt;a href=&quot;\nhttp://picturescream.asia/soft/Rk4&quot; rel=&quot;nofollow&quot; target=&quot;_NEW&quot;&gt;\nhttp://picturescream.asia/soft/Rk4&lt;/a&gt;\n &lt;a href=&quot;\nhttp://picturescream.asia/soft/Rk7&quot; rel=&quot;nofollow&quot; target=&quot;_NEW&quot;&gt;\nhttp://picturescream.asia/soft/Rk7&lt;/a&gt;\n\n\nDuration: 48:22, Format: MP4, Resolution: 1280x720, Size: 1.035 GB","torrent":{"xt":"urn:btih:d0d1f37890afaf27100e808f5f7e970b05762fc4","amp;dn":"Kagney+Linn+Karter+-+Kagney+Linn+Massively+Dicked+Down+HD+720p","amp;tr":["udp%3A%2F%2Ftracker.openbittorrent.com%3A80","udp%3A%2F%2Fopen.demonii.com%3A1337","udp%3A%2F%2Ftracker.coppersurfer.tk%3A6969","udp%3A%2F%2Fexodus.desync.com%3A6969"],"infoHash":"d0d1f37890afaf27100e808f5f7e970b05762fc4","infoHashBuffer":{"type":"Buffer","data":[208,209,243,120,144,175,175,39,16,14,128,143,95,126,151,11,5,118,47,196]},"announce":[],"urlList":[]}}