{"title":"NUBILE FILMS - Janice Griffith - What You Wanted  **NEW**","uid":9567469,"size":237510504,"categoryP":"porn","categoryS":"movie_clips","magnet":"?xt=urn:btih:d14710d846c769e555d92177ac94d2c16e898c77&amp;dn=NUBILE+FILMS+-+Janice+Griffith+-+What+You+Wanted++%2A%2ANEW%2A%2A&amp;tr=udp%3A%2F%2Ftracker.openbittorrent.com%3A80&amp;tr=udp%3A%2F%2Fopen.demonii.com%3A1337&amp;tr=udp%3A%2F%2Ftracker.coppersurfer.tk%3A6969&amp;tr=udp%3A%2F%2Fexodus.desync.com%3A6969","seeders":1,"leechers":1,"uploader":"beta2008x","files":1,"time":1391548003,"description":"\n &lt;a href=&quot;\nhttp://imgboxxx.com/viewer.php?file=3k4wr_nfj.jpg&quot; rel=&quot;nofollow&quot; target=&quot;_NEW&quot;&gt;\nhttp://imgboxxx.com/viewer.php?file=3k4wr_nfj.jpg&lt;/a&gt;\n &lt;a href=&quot;\nhttp://imgboxxx.com/viewer.php?file=ox7vo_nf_janice_griffith_s.jpg&quot; rel=&quot;nofollow&quot; target=&quot;_NEW&quot;&gt;\nhttp://imgboxxx.com/viewer.php?file=ox7vo_nf_janice_griffith_s.jpg&lt;/a&gt;\n\n\n\nteen tiny dancer janice griffith gets pounded hard like a sex doll","torrent":{"xt":"urn:btih:d14710d846c769e555d92177ac94d2c16e898c77","amp;dn":"NUBILE+FILMS+-+Janice+Griffith+-+What+You+Wanted++%2A%2ANEW%2A%2A","amp;tr":["udp%3A%2F%2Ftracker.openbittorrent.com%3A80","udp%3A%2F%2Fopen.demonii.com%3A1337","udp%3A%2F%2Ftracker.coppersurfer.tk%3A6969","udp%3A%2F%2Fexodus.desync.com%3A6969"],"infoHash":"d14710d846c769e555d92177ac94d2c16e898c77","infoHashBuffer":{"type":"Buffer","data":[209,71,16,216,70,199,105,229,85,217,33,119,172,148,210,193,110,137,140,119]},"announce":[],"urlList":[]}}