{"title":"Football.2014.Friendly.(05 mar).Ukraine.v.USA.400p","uid":9706476,"size":1425027702,"categoryP":"video","categoryS":"tv_shows","magnet":"?xt=urn:btih:d4fa018ffb45ca6172b622947ad0ebd8e7503fcd&amp;dn=Football.2014.Friendly.%2805+mar%29.Ukraine.v.USA.400p&amp;tr=udp%3A%2F%2Ftracker.openbittorrent.com%3A80&amp;tr=udp%3A%2F%2Fopen.demonii.com%3A1337&amp;tr=udp%3A%2F%2Ftracker.coppersurfer.tk%3A6969&amp;tr=udp%3A%2F%2Fexodus.desync.com%3A6969","seeders":1,"leechers":0,"uploader":"Nepotu","files":2,"time":1394067740,"description":"Spoken language: ukrainian\n\nCredit: R1CARDO","torrent":{"xt":"urn:btih:d4fa018ffb45ca6172b622947ad0ebd8e7503fcd","amp;dn":"Football.2014.Friendly.%2805+mar%29.Ukraine.v.USA.400p","amp;tr":["udp%3A%2F%2Ftracker.openbittorrent.com%3A80","udp%3A%2F%2Fopen.demonii.com%3A1337","udp%3A%2F%2Ftracker.coppersurfer.tk%3A6969","udp%3A%2F%2Fexodus.desync.com%3A6969"],"infoHash":"d4fa018ffb45ca6172b622947ad0ebd8e7503fcd","infoHashBuffer":{"type":"Buffer","data":[212,250,1,143,251,69,202,97,114,182,34,148,122,208,235,216,231,80,63,205]},"announce":[],"urlList":[]}}