{"title":"Good Morning Vietnam.FR.avi","uid":4468457,"size":725049344,"categoryP":"video","categoryS":"movies","magnet":"?xt=urn:btih:e75a76936e50996d6175486d1446c81db0f4bf5b&amp;dn=Good+Morning+Vietnam.FR.avi&amp;tr=udp%3A%2F%2Ftracker.openbittorrent.com%3A80&amp;tr=udp%3A%2F%2Fopen.demonii.com%3A1337&amp;tr=udp%3A%2F%2Ftracker.coppersurfer.tk%3A6969&amp;tr=udp%3A%2F%2Fexodus.desync.com%3A6969","seeders":1,"leechers":0,"uploader":"Cyb.sdf","files":1,"time":1225020427,"description":"En 1965, le disc-jockey Adrian Cronauer est chargÃƒÆ’Ã‚Â© d'animer un programme de la radio des Forces armÃƒÆ’Ã‚Â©es amÃƒÆ’Ã‚Â©ricaines ÃƒÆ’Ã‚Â  SaÃƒÆ’Ã‚Â¯gon. Mais aux musiques 'lÃƒÆ’Ã‚Â©gÃƒÆ’Ã‚Â¨res' habituellement diffusÃƒÆ’Ã‚Â©es et au conformisme des speakers officiels il prÃƒÆ’Ã‚Â©fÃƒÆ’Ã‚Â¨re le rock et l'humour, multipliant ÃƒÆ’Ã‚Â  l'antenne les plaisanteries de corps de garde, les sketches absurdes, les cris gutturaux et les imitations. Si son extravagance, son irrÃƒÆ’Ã‚Â©ductible insolence et ses choix musicaux font le bonheur des soldats, ils ont toutefois le don d'irriter ses supÃƒÆ’Ã‚Â©rieurs, les sinistres lieutenant Hauk et sergent-major Dickerson...\n\nBonne qualite\n\nCyb","torrent":{"xt":"urn:btih:e75a76936e50996d6175486d1446c81db0f4bf5b","amp;dn":"Good+Morning+Vietnam.FR.avi","amp;tr":["udp%3A%2F%2Ftracker.openbittorrent.com%3A80","udp%3A%2F%2Fopen.demonii.com%3A1337","udp%3A%2F%2Ftracker.coppersurfer.tk%3A6969","udp%3A%2F%2Fexodus.desync.com%3A6969"],"infoHash":"e75a76936e50996d6175486d1446c81db0f4bf5b","infoHashBuffer":{"type":"Buffer","data":[231,90,118,147,110,80,153,109,97,117,72,109,20,70,200,29,176,244,191,91]},"announce":[],"urlList":[]}}