{"title":"Ravishing Thai Girly Boy Gorged Buggered And Sucked","uid":9018095,"size":757812810,"categoryP":"porn","categoryS":"movies","magnet":"?xt=urn:btih:e9fd9ee7427ecbc50e2e6a9a83befb4d8481baf1&amp;dn=Ravishing+Thai+Girly+Boy+Gorged+Buggered+And+Sucked&amp;tr=udp%3A%2F%2Ftracker.openbittorrent.com%3A80&amp;tr=udp%3A%2F%2Fopen.demonii.com%3A1337&amp;tr=udp%3A%2F%2Ftracker.coppersurfer.tk%3A6969&amp;tr=udp%3A%2F%2Fexodus.desync.com%3A6969","seeders":1,"leechers":0,"uploader":"sarah.jensen","files":-1,"time":1381232103,"description":"Kitty pulled her jeans down to a small pair of white briefs. Very sexy, beautiful bottom, lithe curvy hips and long smooth legs. She would be perfect is she had a cock. And she has. And it tasted delicious. She looked down at me with her sweet girly boy looks. She brushed my hair with her silver fingernails, and I looked up at her trembling, and hard. She laughed at me, sweetly. I fucked her small round bottom. Her face was heavenly. You can contact Kitty through the members area, tremble at the video. ","torrent":{"xt":"urn:btih:e9fd9ee7427ecbc50e2e6a9a83befb4d8481baf1","amp;dn":"Ravishing+Thai+Girly+Boy+Gorged+Buggered+And+Sucked","amp;tr":["udp%3A%2F%2Ftracker.openbittorrent.com%3A80","udp%3A%2F%2Fopen.demonii.com%3A1337","udp%3A%2F%2Ftracker.coppersurfer.tk%3A6969","udp%3A%2F%2Fexodus.desync.com%3A6969"],"infoHash":"e9fd9ee7427ecbc50e2e6a9a83befb4d8481baf1","infoHashBuffer":{"type":"Buffer","data":[233,253,158,231,66,126,203,197,14,46,106,154,131,190,251,77,132,129,186,241]},"announce":[],"urlList":[]}}