{"title":"youngfatties - Set 1981 - Carla","uid":9414640,"size":10738438,"categoryP":"porn","categoryS":"pictures","magnet":"?xt=urn:btih:f33a24b295728a3d564e75ca10dc3e70bdebf790&amp;dn=youngfatties+-+Set+1981+-+Carla&amp;tr=udp%3A%2F%2Ftracker.openbittorrent.com%3A80&amp;tr=udp%3A%2F%2Fopen.demonii.com%3A1337&amp;tr=udp%3A%2F%2Ftracker.coppersurfer.tk%3A6969&amp;tr=udp%3A%2F%2Fexodus.desync.com%3A6969","seeders":1,"leechers":0,"uploader":"bestec1234","files":-1,"time":1388364919,"description":" &lt;a href=&quot;\nhttp://bayimg.com/cAfdeaafi&quot; rel=&quot;nofollow&quot; target=&quot;_NEW&quot;&gt;\nhttp://bayimg.com/cAfdeaafi&lt;/a&gt; &lt;a href=&quot;\nhttp://bayimg.com/cAFdfaaFI&quot; rel=&quot;nofollow&quot; target=&quot;_NEW&quot;&gt;\nhttp://bayimg.com/cAFdfaaFI&lt;/a&gt; &lt;a href=&quot;\nhttp://bayimg.com/caFdgaafI&quot; rel=&quot;nofollow&quot; target=&quot;_NEW&quot;&gt;\nhttp://bayimg.com/caFdgaafI&lt;/a&gt; &lt;a href=&quot;\nhttp://bayimg.com/cafDHaafi&quot; rel=&quot;nofollow&quot; target=&quot;_NEW&quot;&gt;\nhttp://bayimg.com/cafDHaafi&lt;/a&gt; &lt;a href=&quot;\nhttp://bayimg.com/CaFDiAaFi&quot; rel=&quot;nofollow&quot; target=&quot;_NEW&quot;&gt;\nhttp://bayimg.com/CaFDiAaFi&lt;/a&gt; &lt;a href=&quot;\nhttp://bayimg.com/CAFDjaAFI&quot; rel=&quot;nofollow&quot; target=&quot;_NEW&quot;&gt;\nhttp://bayimg.com/CAFDjaAFI&lt;/a&gt;\n\n","torrent":{"xt":"urn:btih:f33a24b295728a3d564e75ca10dc3e70bdebf790","amp;dn":"youngfatties+-+Set+1981+-+Carla","amp;tr":["udp%3A%2F%2Ftracker.openbittorrent.com%3A80","udp%3A%2F%2Fopen.demonii.com%3A1337","udp%3A%2F%2Ftracker.coppersurfer.tk%3A6969","udp%3A%2F%2Fexodus.desync.com%3A6969"],"infoHash":"f33a24b295728a3d564e75ca10dc3e70bdebf790","infoHashBuffer":{"type":"Buffer","data":[243,58,36,178,149,114,138,61,86,78,117,202,16,220,62,112,189,235,247,144]},"announce":[],"urlList":[]}}